moboard/__init__.py
moboard-0.1.0.dist-info/METADATA
moboard-0.1.0.dist-info/WHEEL
moboard-0.1.0.dist-info/licenses/LICENSE
moboard-0.1.0.dist-info/RECORD
