Metadata-Version: 2.4
Name: moboard
Version: 0.1.0
Summary: A Python package for fresh data processing
Project-URL: Homepage, https://github.com/vincentwarmerdam/moboard
Project-URL: Bug Tracker, https://github.com/vincentwarmerdam/moboard/issues
Author: Vincent Warmerdam
License-File: LICENSE
Classifier: License :: OSI Approved :: MIT License
Classifier: Operating System :: OS Independent
Classifier: Programming Language :: Python :: 3
Requires-Python: >=3.10
Requires-Dist: anywidget
Provides-Extra: alt
Requires-Dist: altair; extra == 'alt'
Requires-Dist: vl-convert-python; extra == 'alt'
Provides-Extra: dev
Requires-Dist: marimo; extra == 'dev'
Requires-Dist: mohtml; extra == 'dev'
Requires-Dist: polars; extra == 'dev'
Requires-Dist: pytest; extra == 'dev'
